discohooker/__init__.py
discohooker/embed.py
discohooker/errors.py
discohooker/message.py
discohooker/tasks.py
discohooker/webhook.py
discohooker-1.0.6.dist-info/LICENSE
discohooker-1.0.6.dist-info/METADATA
discohooker-1.0.6.dist-info/WHEEL
discohooker-1.0.6.dist-info/top_level.txt
discohooker-1.0.6.dist-info/RECORD
