Metadata-Version: 2.1
Name: discohooker
Version: 1.0.6
Summary: A easy PyPI to send Discord Webhook!
Home-page: https://replit.com/@MAX110331/discohooker
Author: MaxPython110331
Author-email: max.gamil110331@gmail.com
License: MIT
Classifier: Programming Language :: Python :: 3
Classifier: License :: OSI Approved :: MIT License
Classifier: Operating System :: OS Independent
Requires-Python: >=3.6
License-File: LICENSE
Requires-Dist: requests
Requires-Dist: datetime
Requires-Dist: pytz
